odoo/addons/sale_order_blanket_order_stock_prebook/README.rst
odoo/addons/sale_order_blanket_order_stock_prebook/__init__.py
odoo/addons/sale_order_blanket_order_stock_prebook/__manifest__.py
odoo/addons/sale_order_blanket_order_stock_prebook/i18n/fr.po
odoo/addons/sale_order_blanket_order_stock_prebook/i18n/it.po
odoo/addons/sale_order_blanket_order_stock_prebook/i18n/sale_order_blanket_order_stock_prebook.pot
odoo/addons/sale_order_blanket_order_stock_prebook/models/__init__.py
odoo/addons/sale_order_blanket_order_stock_prebook/models/sale_order.py
odoo/addons/sale_order_blanket_order_stock_prebook/models/sale_order_line.py
odoo/addons/sale_order_blanket_order_stock_prebook/readme/CONTEXT.md
odoo/addons/sale_order_blanket_order_stock_prebook/readme/CONTRIBUTORS.md
odoo/addons/sale_order_blanket_order_stock_prebook/readme/CREDITS.md
odoo/addons/sale_order_blanket_order_stock_prebook/readme/DESCRIPTION.md
odoo/addons/sale_order_blanket_order_stock_prebook/readme/USAGE.md
odoo/addons/sale_order_blanket_order_stock_prebook/static/description/icon.png
odoo/addons/sale_order_blanket_order_stock_prebook/static/description/index.html
odoo/addons/sale_order_blanket_order_stock_prebook/tests/__init__.py
odoo/addons/sale_order_blanket_order_stock_prebook/tests/common.py
odoo/addons/sale_order_blanket_order_stock_prebook/tests/test_sale_blanket_order.py
odoo/addons/sale_order_blanket_order_stock_prebook/tests/test_sale_call_off_order.py
odoo_addon_sale_order_blanket_order_stock_prebook-16.0.1.0.0.6.dist-info/METADATA
odoo_addon_sale_order_blanket_order_stock_prebook-16.0.1.0.0.6.dist-info/WHEEL
odoo_addon_sale_order_blanket_order_stock_prebook-16.0.1.0.0.6.dist-info/top_level.txt
odoo_addon_sale_order_blanket_order_stock_prebook-16.0.1.0.0.6.dist-info/RECORD
